{
  "beijing": {
    "province": "北京",
    "province_code": "beijing",
    "92_gasoline": 7.18,
    "95_gasoline": 7.64,
    "98_gasoline": 9.14,
    "0_diesel": 6.87,
    "currency": "CNY",
    "unit": "yuan/liter",
    "update_date": "2026-07-08",
    "source_url": "http://m.qiyoujiage.com/beijing.shtml",
    "adjustment": {
      "next_adjustment_date": "7月17日"
    }
  },
  "shanghai": {
    "province": "上海",
    "province_code": "shanghai",
    "92_gasoline": 7.14,
    "95_gasoline": 7.6,
    "98_gasoline": 9.6,
    "0_diesel": 6.8,
    "currency": "CNY",
    "unit": "yuan/liter",
    "update_date": "2026-07-08",
    "source_url": "http://m.qiyoujiage.com/shanghai.shtml",
    "adjustment": {
      "next_adjustment_date": "7月17日"
    }
  },
  "tianjin": {
    "province": "天津",
    "province_code": "tianjin",
    "92_gasoline": 7.17,
    "95_gasoline": 7.57,
    "98_gasoline": 9.07,
    "0_diesel": 6.82,
    "currency": "CNY",
    "unit": "yuan/liter",
    "update_date": "2026-07-08",
    "source_url": "http://m.qiyoujiage.com/tianjin.shtml",
    "adjustment": {
      "next_adjustment_date": "7月17日"
    }
  },
  "chongqing": {
    "province": "重庆",
    "province_code": "chongqing",
    "92_gasoline": 7.25,
    "95_gasoline": 7.66,
    "98_gasoline": 9.24,
    "0_diesel": 6.9,
    "currency": "CNY",
    "unit": "yuan/liter",
    "update_date": "2026-07-08",
    "source_url": "http://m.qiyoujiage.com/chongqing.shtml",
    "adjustment": {
      "next_adjustment_date": "7月17日"
    }
  },
  "hebei": {
    "province": "河北",
    "province_code": "hebei",
    "92_gasoline": 7.17,
    "95_gasoline": 7.57,
    "98_gasoline": 8.39,
    "0_diesel": 6.82,
    "currency": "CNY",
    "unit": "yuan/liter",
    "update_date": "2026-07-08",
    "source_url": "http://m.qiyoujiage.com/hebei.shtml",
    "adjustment": {
      "next_adjustment_date": "7月17日"
    }
  },
  "shanxi": {
    "province": "山西",
    "province_code": "shanxi",
    "92_gasoline": 7.13,
    "95_gasoline": 7.7,
    "98_gasoline": 8.88,
    "0_diesel": 6.89,
    "currency": "CNY",
    "unit": "yuan/liter",
    "update_date": "2026-07-08",
    "source_url": "http://m.qiyoujiage.com/shanxi.shtml",
    "adjustment": {
      "next_adjustment_date": "7月17日"
    }
  },
  "neimenggu": {
    "province": "内蒙古",
    "province_code": "neimenggu",
    "92_gasoline": 7.18,
    "95_gasoline": 7.63,
    "98_gasoline": 8.33,
    "0_diesel": 6.69,
    "currency": "CNY",
    "unit": "yuan/liter",
    "update_date": "2026-07-08",
    "source_url": "http://m.qiyoujiage.com/neimenggu.shtml",
    "adjustment": {
      "next_adjustment_date": "7月17日"
    }
  },
  "liaoning": {
    "province": "辽宁",
    "province_code": "liaoning",
    "92_gasoline": 7.23,
    "95_gasoline": 7.73,
    "98_gasoline": 8.47,
    "0_diesel": 6.73,
    "currency": "CNY",
    "unit": "yuan/liter",
    "update_date": "2026-07-08",
    "source_url": "http://m.qiyoujiage.com/liaoning.shtml",
    "adjustment": {
      "next_adjustment_date": "7月17日"
    }
  },
  "jilin": {
    "province": "吉林",
    "province_code": "jilin",
    "92_gasoline": 7.14,
    "95_gasoline": 7.7,
    "98_gasoline": 8.39,
    "0_diesel": 6.74,
    "currency": "CNY",
    "unit": "yuan/liter",
    "update_date": "2026-07-08",
    "source_url": "http://m.qiyoujiage.com/jilin.shtml",
    "adjustment": {
      "next_adjustment_date": "7月17日"
    }
  },
  "heilongjiang": {
    "province": "黑龙江",
    "province_code": "heilongjiang",
    "92_gasoline": 7.14,
    "95_gasoline": 7.65,
    "98_gasoline": 8.68,
    "0_diesel": 6.64,
    "currency": "CNY",
    "unit": "yuan/liter",
    "update_date": "2026-07-08",
    "source_url": "http://m.qiyoujiage.com/heilongjiang.shtml",
    "adjustment": {
      "next_adjustment_date": "7月17日"
    }
  },
  "jiangsu": {
    "province": "江苏",
    "province_code": "jiangsu",
    "92_gasoline": 7.15,
    "95_gasoline": 7.61,
    "98_gasoline": 9.68,
    "0_diesel": 6.79,
    "currency": "CNY",
    "unit": "yuan/liter",
    "update_date": "2026-07-08",
    "source_url": "http://m.qiyoujiage.com/jiangsu.shtml",
    "adjustment": {
      "next_adjustment_date": "7月17日"
    }
  },
  "zhejiang": {
    "province": "浙江",
    "province_code": "zhejiang",
    "92_gasoline": 7.15,
    "95_gasoline": 7.61,
    "98_gasoline": 9.11,
    "0_diesel": 6.81,
    "currency": "CNY",
    "unit": "yuan/liter",
    "update_date": "2026-07-08",
    "source_url": "http://m.qiyoujiage.com/zhejiang.shtml",
    "adjustment": {
      "next_adjustment_date": "7月17日"
    }
  },
  "anhui": {
    "province": "安徽",
    "province_code": "anhui",
    "92_gasoline": 7.14,
    "95_gasoline": 7.65,
    "98_gasoline": 9.15,
    "0_diesel": 6.86,
    "currency": "CNY",
    "unit": "yuan/liter",
    "update_date": "2026-07-08",
    "source_url": "http://m.qiyoujiage.com/anhui.shtml",
    "adjustment": {
      "next_adjustment_date": "7月17日"
    }
  },
  "fujian": {
    "province": "福建",
    "province_code": "fujian",
    "92_gasoline": 7.15,
    "95_gasoline": 7.63,
    "98_gasoline": 9.13,
    "0_diesel": 6.82,
    "currency": "CNY",
    "unit": "yuan/liter",
    "update_date": "2026-07-08",
    "source_url": "http://m.qiyoujiage.com/fujian.shtml",
    "adjustment": {
      "next_adjustment_date": "7月17日"
    }
  },
  "jiangxi": {
    "province": "江西",
    "province_code": "jiangxi",
    "92_gasoline": 7.14,
    "95_gasoline": 7.67,
    "98_gasoline": 8.27,
    "0_diesel": 6.87,
    "currency": "CNY",
    "unit": "yuan/liter",
    "update_date": "2026-07-08",
    "source_url": "http://m.qiyoujiage.com/jiangxi.shtml",
    "adjustment": {
      "next_adjustment_date": "7月17日"
    }
  },
  "shandong": {
    "province": "山东",
    "province_code": "shandong",
    "92_gasoline": 7.14,
    "95_gasoline": 7.66,
    "98_gasoline": 8.66,
    "0_diesel": 6.74,
    "currency": "CNY",
    "unit": "yuan/liter",
    "update_date": "2026-07-08",
    "source_url": "http://m.qiyoujiage.com/shandong.shtml",
    "adjustment": {
      "next_adjustment_date": "7月17日"
    }
  },
  "henan": {
    "province": "河南",
    "province_code": "henan",
    "92_gasoline": 7.18,
    "95_gasoline": 7.67,
    "98_gasoline": 8.32,
    "0_diesel": 6.81,
    "currency": "CNY",
    "unit": "yuan/liter",
    "update_date": "2026-07-08",
    "source_url": "http://m.qiyoujiage.com/henan.shtml",
    "adjustment": {
      "next_adjustment_date": "7月17日"
    }
  },
  "hubei": {
    "province": "湖北",
    "province_code": "hubei",
    "92_gasoline": 7.19,
    "95_gasoline": 7.69,
    "98_gasoline": 9.69,
    "0_diesel": 6.81,
    "currency": "CNY",
    "unit": "yuan/liter",
    "update_date": "2026-07-08",
    "source_url": "http://m.qiyoujiage.com/hubei.shtml",
    "adjustment": {
      "next_adjustment_date": "7月17日"
    }
  },
  "hunan": {
    "province": "湖南",
    "province_code": "hunan",
    "92_gasoline": 7.13,
    "95_gasoline": 7.58,
    "98_gasoline": 8.78,
    "0_diesel": 6.89,
    "currency": "CNY",
    "unit": "yuan/liter",
    "update_date": "2026-07-08",
    "source_url": "http://m.qiyoujiage.com/hunan.shtml",
    "adjustment": {
      "next_adjustment_date": "7月17日"
    }
  },
  "guangdong": {
    "province": "广东",
    "province_code": "guangdong",
    "92_gasoline": 7.2,
    "95_gasoline": 7.8,
    "98_gasoline": 9.8,
    "0_diesel": 6.83,
    "currency": "CNY",
    "unit": "yuan/liter",
    "update_date": "2026-07-08",
    "source_url": "http://m.qiyoujiage.com/guangdong.shtml",
    "adjustment": {
      "next_adjustment_date": "7月17日"
    }
  },
  "guangxi": {
    "province": "广西",
    "province_code": "guangxi",
    "92_gasoline": 7.24,
    "95_gasoline": 7.82,
    "98_gasoline": 9.1,
    "0_diesel": 6.88,
    "currency": "CNY",
    "unit": "yuan/liter",
    "update_date": "2026-07-08",
    "source_url": "http://m.qiyoujiage.com/guangxi.shtml",
    "adjustment": {
      "next_adjustment_date": "7月17日"
    }
  },
  "hainan": {
    "province": "海南",
    "province_code": "hainan",
    "92_gasoline": 8.29,
    "95_gasoline": 8.8,
    "98_gasoline": 9.8,
    "0_diesel": 6.91,
    "currency": "CNY",
    "unit": "yuan/liter",
    "update_date": "2026-07-08",
    "source_url": "http://m.qiyoujiage.com/hainan.shtml",
    "adjustment": {
      "next_adjustment_date": "7月17日"
    }
  },
  "sichuan": {
    "province": "四川",
    "province_code": "sichuan",
    "92_gasoline": 7.28,
    "95_gasoline": 7.78,
    "98_gasoline": 8.88,
    "0_diesel": 6.88,
    "currency": "CNY",
    "unit": "yuan/liter",
    "update_date": "2026-07-08",
    "source_url": "http://m.qiyoujiage.com/sichuan.shtml",
    "adjustment": {
      "next_adjustment_date": "7月17日"
    }
  },
  "guizhou": {
    "province": "贵州",
    "province_code": "guizhou",
    "92_gasoline": 7.31,
    "95_gasoline": 7.72,
    "98_gasoline": 8.72,
    "0_diesel": 6.93,
    "currency": "CNY",
    "unit": "yuan/liter",
    "update_date": "2026-07-08",
    "source_url": "http://m.qiyoujiage.com/guizhou.shtml",
    "adjustment": {
      "next_adjustment_date": "7月17日"
    }
  },
  "yunnan": {
    "province": "云南",
    "province_code": "yunnan",
    "92_gasoline": 7.32,
    "95_gasoline": 7.86,
    "98_gasoline": 8.54,
    "0_diesel": 6.9,
    "currency": "CNY",
    "unit": "yuan/liter",
    "update_date": "2026-07-08",
    "source_url": "http://m.qiyoujiage.com/yunnan.shtml",
    "adjustment": {
      "next_adjustment_date": "7月17日"
    }
  },
  "xizang": {
    "province": "西藏",
    "province_code": "xizang",
    "92_gasoline": 8.06,
    "95_gasoline": 8.53,
    "98_gasoline": 9.5,
    "0_diesel": 7.37,
    "currency": "CNY",
    "unit": "yuan/liter",
    "update_date": "2026-07-08",
    "source_url": "http://m.qiyoujiage.com/xizang.shtml",
    "adjustment": {
      "next_adjustment_date": "7月17日"
    }
  },
  "shanxi-3": {
    "province": "陕西",
    "province_code": "shanxi-3",
    "92_gasoline": 7.07,
    "95_gasoline": 7.47,
    "98_gasoline": 8.54,
    "0_diesel": 6.72,
    "currency": "CNY",
    "unit": "yuan/liter",
    "update_date": "2026-07-08",
    "source_url": "http://m.qiyoujiage.com/shanxi-3.shtml",
    "adjustment": {
      "next_adjustment_date": "7月17日"
    }
  },
  "gansu": {
    "province": "甘肃",
    "province_code": "gansu",
    "92_gasoline": 7.17,
    "95_gasoline": 7.66,
    "98_gasoline": 8.23,
    "0_diesel": 6.73,
    "currency": "CNY",
    "unit": "yuan/liter",
    "update_date": "2026-07-08",
    "source_url": "http://m.qiyoujiage.com/gansu.shtml",
    "adjustment": {
      "next_adjustment_date": "7月17日"
    }
  },
  "qinghai": {
    "province": "青海",
    "province_code": "qinghai",
    "92_gasoline": 7.13,
    "95_gasoline": 7.65,
    "98_gasoline": 8.33,
    "0_diesel": 6.75,
    "currency": "CNY",
    "unit": "yuan/liter",
    "update_date": "2026-07-08",
    "source_url": "http://m.qiyoujiage.com/qinghai.shtml",
    "adjustment": {
      "next_adjustment_date": "7月17日"
    }
  },
  "ningxia": {
    "province": "宁夏",
    "province_code": "ningxia",
    "92_gasoline": 7.08,
    "95_gasoline": 7.48,
    "98_gasoline": 8.55,
    "0_diesel": 6.72,
    "currency": "CNY",
    "unit": "yuan/liter",
    "update_date": "2026-07-08",
    "source_url": "http://m.qiyoujiage.com/ningxia.shtml",
    "adjustment": {
      "next_adjustment_date": "7月17日"
    }
  },
  "xinjiang": {
    "province": "新疆",
    "province_code": "xinjiang",
    "92_gasoline": 6.98,
    "95_gasoline": 7.46,
    "98_gasoline": 8.34,
    "0_diesel": 6.61,
    "currency": "CNY",
    "unit": "yuan/liter",
    "update_date": "2026-07-08",
    "source_url": "http://m.qiyoujiage.com/xinjiang.shtml",
    "adjustment": {
      "next_adjustment_date": "7月17日"
    }
  }
}